<?xml version="1.0" encoding="UTF-8"?>
<!DOCTYPE tiles-definitions PUBLIC
        "-//Apache Software Foundation//DTD Tiles Configuration 3.0//EN"
        "http://tiles.apache.org/dtds/tiles-config_3_0.dtd">

<tiles-definitions>
    <definition name="rooms/all" extends="default">
        <put-attribute name="title" value="All Rooms" />
        <put-attribute name="body" value="/WEB-INF/pages/rooms/all.jsp" />
    </definition>
    <definition name="rooms/add" extends="default">
        <put-attribute name="title" value="Add Room"/>
        <put-attribute name="body" value="/WEB-INF/pages/rooms/add.jsp"/>
        <put-attribute name="additionalScripts" value="/WEB-INF/pages/rooms/room-add-scripts.jsp"/>
    </definition>
    <definition name="rooms/edit" extends="default">
        <put-attribute name="title" value="Add Room"/>
        <put-attribute name="body" value="/WEB-INF/pages/rooms/edit.jsp"/>
        <put-attribute name="additionalScripts" value="/WEB-INF/pages/rooms/room-add-scripts.jsp"/>
    </definition>
    <definition name="rooms/info" extends="default">
        <put-attribute name="title" value="Room's Calendar"/>
        <put-attribute name="body" value="/WEB-INF/pages/rooms/info.jsp"/>
        <put-attribute name="additionalScripts" value="/WEB-INF/pages/rooms/room-info-scripts.jsp"/>
    </definition>
    <definition name="rooms/add/event" extends="default">
        <put-attribute name="title" value="Add Event"/>
        <put-attribute name="body" value="/WEB-INF/pages/rooms/add-event.jsp"/>
        <put-attribute name="additionalScripts" value="/WEB-INF/pages/rooms/additionalScripts.jsp"/>
    </definition>
</tiles-definitions>